thorcast_api_client/__init__.py
thorcast_api_client/auth.py
thorcast_api_client/client.py
thorcast_api_client/config.py
thorcast_api_client/exceptions.py
thorcast_api_client-0.1.4.2.dist-info/METADATA
thorcast_api_client-0.1.4.2.dist-info/WHEEL
thorcast_api_client-0.1.4.2.dist-info/RECORD
