Metadata-Version: 2.3
Name: thorcast_api_client
Version: 0.1.4.2
Summary: Un client Python pour interagir avec l'API ThorCast
Author: JBCAYRE
Author-email: jcayre@mint.eco
Requires-Python: >=3.8,<4.0
Classifier: Programming Language :: Python :: 3
Classifier: Programming Language :: Python :: 3.8
Classifier: Programming Language :: Python :: 3.9
Classifier: Programming Language :: Python :: 3.10
Classifier: Programming Language :: Python :: 3.11
Classifier: Programming Language :: Python :: 3.12
Classifier: Programming Language :: Python :: 3.13
Requires-Dist: requests (>=2.26.0,<3.0.0)
